huti/__init__.py
huti/constants.py
huti-0.1.23.dist-info/LICENSE
huti-0.1.23.dist-info/METADATA
huti-0.1.23.dist-info/WHEEL
huti-0.1.23.dist-info/top_level.txt
huti-0.1.23.dist-info/RECORD
