Metadata-Version: 2.1
Name: huti
Version: 0.1.23
Summary: Python helpers and utilities
Author-email: José Antonio Puértolas Montañés <63794670+j5pu@users.noreply.github.com>
License: MIT
Project-URL: Homepage, https://github.com/j5pu/huti
Requires-Python: >=3.11
License-File: LICENSE
Provides-Extra: dev
Requires-Dist: pproj[all] ; extra == 'dev'
